chexus/__init__.py
chexus/__main__.py
chexus/hdf5.py
chexus/io.py
chexus/json.py
chexus/py.typed
chexus/tree.py
chexus/validate.py
chexus/validators.py
chexus-25.1.0.dist-info/LICENSE
chexus-25.1.0.dist-info/METADATA
chexus-25.1.0.dist-info/WHEEL
chexus-25.1.0.dist-info/entry_points.txt
chexus-25.1.0.dist-info/top_level.txt
chexus-25.1.0.dist-info/RECORD
