Metadata-Version: 2.2
Name: chexus
Version: 25.1.0
Summary: Validate and check NeXus files
Author: Scipp contributors
License: BSD 3-Clause License
Project-URL: Bug Tracker, https://github.com/scipp/chexus/issues
Project-URL: Documentation, https://scipp.github.io/chexus
Project-URL: Source, https://github.com/scipp/chexus
Classifier: Intended Audience :: Science/Research
Classifier: License :: OSI Approved :: BSD License
Classifier: Natural Language :: English
Classifier: Operating System :: OS Independent
Classifier: Programming Language :: Python :: 3
Classifier: Programming Language :: Python :: 3 :: Only
Classifier: Programming Language :: Python :: 3.10
Classifier: Programming Language :: Python :: 3.11
Classifier: Programming Language :: Python :: 3.12
Classifier: Topic :: Scientific/Engineering
Classifier: Typing :: Typed
Requires-Python: >=3.10
License-File: LICENSE
Requires-Dist: h5py
Provides-Extra: test
Requires-Dist: pytest; extra == "test"
Requires-Dist: scipp; extra == "test"
